{
  "project_info": {
    "project_number": "950617506217",
    "project_id": "cloud-a53c0",
    "storage_bucket": "cloud-a53c0.appspot.com"
  },
  "client": [
    {
      "client_info": {
        "mobilesdk_app_id": "1:950617506217:android:6eb1b23e0a2151045cc4b8",
        "android_client_info": {
          "package_name": "com.example.myapplication"
        }
      },
      "oauth_client": [
        {
          "client_id": "950617506217-mt5pq5fd8hombg5kfcgsnig4lp2b5mi7.apps.googleusercontent.com",
          "client_type": 3
        }
      ],
      "api_key": [
        {
          "current_key": "AIzaSyATafCfqFU6uVgOCcHmLXi0LmlAjl4_t0w"
        }
      ],
      "services": {
        "appinvite_service": {
          "other_platform_oauth_client": [
            {
              "client_id": "950617506217-mt5pq5fd8hombg5kfcgsnig4lp2b5mi7.apps.googleusercontent.com",
              "client_type": 3
            }
          ]
        }
      }
    }
  ],
  "configuration_version": "1"
}